Workbook

Sheet READ ME
A1: FinTech Tape — v3 (Comps matches your CapIQ layout; 293-ticker map pre-loaded)
A3: ONE-TIME: paste your two precedent tabs into 'M&A' and 'Raises' (cols A-K). 'Subsector Map' is already filled.
A5: COMPS BACKFILL (per quarter-end snapshot):
A6: 1. In your CapIQ Comps Detail tab, set the date cell D3 to a quarter-end (e.g. 31-Mar-2022). Let it recalc.
A7: 2. Select the data block (Display Name ... Gross Margin) and COPY.
A8: 3. In this file's 'Comps' sheet, go to the first empty row, click cell B, and PASTE SPECIAL -> VALUES.
A9: (Values only — the CapIQ cells are live formulas that change when you move D3.)
A10: 4. In column A for those pasted rows, type the same quarter-end date and fill down.
A11: 5. Repeat for each quarter-end back to 2022. Columns AY-BC (Subsector, Fwd EV/Rev...) auto-compute.
A13: Then 'Multiples' shows median forward EV/Rev by subsector by snapshot. Put your snapshot dates in row 4.

Sheet M&A
A1: Sector | B1: Target Country | C1: Deal Type | D1: Date | E1: Target | F1: Acquirer | G1: EV ($M) | H1: EV / Revenue | I1: EV / EBITDA | J1: Target Description | K1: Link / Press Release | L1: Quarter
A2: Banking & Lending Tech | B2: US | C2: Take-Private | D2: 46189 | E2: Open Lending | F2: ANV Group | G2: 372 | J2: Auto lending software | K2: link | L2: =IF(D2="","",YEAR(D2)&"-Q"&ROUNDUP(MONTH(D2)/3,0))
A3: Payments | B3: US | C3: Strategic M&A | D3: 46191 | E3: Celero Commerce | F3: Deluxe | G3: 625 | J3: SMB processing | K3: link | L3: =IF(D3="","",YEAR(D3)&"-Q"&ROUNDUP(MONTH(D3)/3,0))
L4: =IF(D4="","",YEAR(D4)&"-Q"&ROUNDUP(MONTH(D4)/3,0))
L5: =IF(D5="","",YEAR(D5)&"-Q"&ROUNDUP(MONTH(D5)/3,0))
L6: =IF(D6="","",YEAR(D6)&"-Q"&ROUNDUP(MONTH(D6)/3,0))
L7: =IF(D7="","",YEAR(D7)&"-Q"&ROUNDUP(MONTH(D7)/3,0))
L8: =IF(D8="","",YEAR(D8)&"-Q"&ROUNDUP(MONTH(D8)/3,0))
L9: =IF(D9="","",YEAR(D9)&"-Q"&ROUNDUP(MONTH(D9)/3,0))
L10: =IF(D10="","",YEAR(D10)&"-Q"&ROUNDUP(MONTH(D10)/3,0))
L11: =IF(D11="","",YEAR(D11)&"-Q"&ROUNDUP(MONTH(D11)/3,0))
L12: =IF(D12="","",YEAR(D12)&"-Q"&ROUNDUP(MONTH(D12)/3,0))
L13: =IF(D13="","",YEAR(D13)&"-Q"&ROUNDUP(MONTH(D13)/3,0))
L14: =IF(D14="","",YEAR(D14)&"-Q"&ROUNDUP(MONTH(D14)/3,0))
L15: =IF(D15="","",YEAR(D15)&"-Q"&ROUNDUP(MONTH(D15)/3,0))
... L1000: =IF(D1000="","",YEAR(D1000)&"-Q"&ROUNDUP(MONTH(D1000)/3,0))

Sheet Raises
A1: Sector | B1: Target Country | C1: Date | D1: Target | E1: Lead Investor(s) | F1: Amount ($M) | G1: Valuation ($M) | H1: EV / Revenue | I1: EV / EBITDA | J1: Target Description | K1: Link / Press Release | L1: Quarter
A2: Banking & Lending Tech | B2: Saudi Arabia | C2: 46187 | D2: D360 Bank | E2: PIF / Derayah | F2: 400 | G2: 1600 | J2: Digital bank | K2: link | L2: =IF(C2="","",YEAR(C2)&"-Q"&ROUNDUP(MONTH(C2)/3,0))
A3: Payments | B3: US | C3: 46188 | D3: Interchecks | E3: Bettor Capital | F3: 50 | J3: Instant payments | K3: link | L3: =IF(C3="","",YEAR(C3)&"-Q"&ROUNDUP(MONTH(C3)/3,0))
L4: =IF(C4="","",YEAR(C4)&"-Q"&ROUNDUP(MONTH(C4)/3,0))
L5: =IF(C5="","",YEAR(C5)&"-Q"&ROUNDUP(MONTH(C5)/3,0))
L6: =IF(C6="","",YEAR(C6)&"-Q"&ROUNDUP(MONTH(C6)/3,0))
L7: =IF(C7="","",YEAR(C7)&"-Q"&ROUNDUP(MONTH(C7)/3,0))
L8: =IF(C8="","",YEAR(C8)&"-Q"&ROUNDUP(MONTH(C8)/3,0))
L9: =IF(C9="","",YEAR(C9)&"-Q"&ROUNDUP(MONTH(C9)/3,0))
L10: =IF(C10="","",YEAR(C10)&"-Q"&ROUNDUP(MONTH(C10)/3,0))
L11: =IF(C11="","",YEAR(C11)&"-Q"&ROUNDUP(MONTH(C11)/3,0))
L12: =IF(C12="","",YEAR(C12)&"-Q"&ROUNDUP(MONTH(C12)/3,0))
L13: =IF(C13="","",YEAR(C13)&"-Q"&ROUNDUP(MONTH(C13)/3,0))
L14: =IF(C14="","",YEAR(C14)&"-Q"&ROUNDUP(MONTH(C14)/3,0))
L15: =IF(C15="","",YEAR(C15)&"-Q"&ROUNDUP(MONTH(C15)/3,0))
... L1000: =IF(C1000="","",YEAR(C1000)&"-Q"&ROUNDUP(MONTH(C1000)/3,0))

Sheet Rotation
A1: SECTOR ROTATION — capital ($M) by subsector by quarter
A3: Subsector ($M) | B3: 2025-Q3 | C3: 2025-Q4 | D3: 2026-Q1 | E3: 2026-Q2
A4: Asset & Wealth Tech | B4: =SUMIFS('M&A'!$G:$G,'M&A'!$A:$A,$A4,'M&A'!$L:$L,B$3)+SUMIFS(Raises!$F:$F,Raises!$A:$A,$A4,Raises!$L:$L,B$3) | C4: =SUMIFS('M&A'!$G:$G,'M&A'!$A:$A,$A4,'M&A'!$L:$L,C$3)+SUMIFS(Raises!$F:$F,Raises!$A:$A,$A4,Raises!$L:$L,C$3) | D4: =SUMIFS('M&A'!$G:$G,'M&A'!$A:$A,$A4,'M&A'!$L:$L,D$3)+SUMIFS(Raises!$F:$F,Raises!$A:$A,$A4,Raises!$L:$L,D$3) | E4: =SUMIFS('M&A'!$G:$G,'M&A'!$A:$A,$A4,'M&A'!$L:$L,E$3)+SUMIFS(Raises!$F:$F,Raises!$A:$A,$A4,Raises!$L:$L,E$3)
A5: Banking & Lending Tech | B5: =SUMIFS('M&A'!$G:$G,'M&A'!$A:$A,$A5,'M&A'!$L:$L,B$3)+SUMIFS(Raises!$F:$F,Raises!$A:$A,$A5,Raises!$L:$L,B$3) | C5: =SUMIFS('M&A'!$G:$G,'M&A'!$A:$A,$A5,'M&A'!$L:$L,C$3)+SUMIFS(Raises!$F:$F,Raises!$A:$A,$A5,Raises!$L:$L,C$3) | D5: =SUMIFS('M&A'!$G:$G,'M&A'!$A:$A,$A5,'M&A'!$L:$L,D$3)+SUMIFS(Raises!$F:$F,Raises!$A:$A,$A5,Raises!$L:$L,D$3) | E5: =SUMIFS('M&A'!$G:$G,'M&A'!$A:$A,$A5,'M&A'!$L:$L,E$3)+SUMIFS(Raises!$F:$F,Raises!$A:$A,$A5,Raises!$L:$L,E$3)
A6: Capital Markets Tech | B6: =SUMIFS('M&A'!$G:$G,'M&A'!$A:$A,$A6,'M&A'!$L:$L,B$3)+SUMIFS(Raises!$F:$F,Raises!$A:$A,$A6,Raises!$L:$L,B$3) | C6: =SUMIFS('M&A'!$G:$G,'M&A'!$A:$A,$A6,'M&A'!$L:$L,C$3)+SUMIFS(Raises!$F:$F,Raises!$A:$A,$A6,Raises!$L:$L,C$3) | D6: =SUMIFS('M&A'!$G:$G,'M&A'!$A:$A,$A6,'M&A'!$L:$L,D$3)+SUMIFS(Raises!$F:$F,Raises!$A:$A,$A6,Raises!$L:$L,D$3) | E6: =SUMIFS('M&A'!$G:$G,'M&A'!$A:$A,$A6,'M&A'!$L:$L,E$3)+SUMIFS(Raises!$F:$F,Raises!$A:$A,$A6,Raises!$L:$L,E$3)
A7: Corporate Financial Function | B7: =SUMIFS('M&A'!$G:$G,'M&A'!$A:$A,$A7,'M&A'!$L:$L,B$3)+SUMIFS(Raises!$F:$F,Raises!$A:$A,$A7,Raises!$L:$L,B$3) | C7: =SUMIFS('M&A'!$G:$G,'M&A'!$A:$A,$A7,'M&A'!$L:$L,C$3)+SUMIFS(Raises!$F:$F,Raises!$A:$A,$A7,Raises!$L:$L,C$3) | D7: =SUMIFS('M&A'!$G:$G,'M&A'!$A:$A,$A7,'M&A'!$L:$L,D$3)+SUMIFS(Raises!$F:$F,Raises!$A:$A,$A7,Raises!$L:$L,D$3) | E7: =SUMIFS('M&A'!$G:$G,'M&A'!$A:$A,$A7,'M&A'!$L:$L,E$3)+SUMIFS(Raises!$F:$F,Raises!$A:$A,$A7,Raises!$L:$L,E$3)
A8: Financial Info & Analytics | B8: =SUMIFS('M&A'!$G:$G,'M&A'!$A:$A,$A8,'M&A'!$L:$L,B$3)+SUMIFS(Raises!$F:$F,Raises!$A:$A,$A8,Raises!$L:$L,B$3) | C8: =SUMIFS('M&A'!$G:$G,'M&A'!$A:$A,$A8,'M&A'!$L:$L,C$3)+SUMIFS(Raises!$F:$F,Raises!$A:$A,$A8,Raises!$L:$L,C$3) | D8: =SUMIFS('M&A'!$G:$G,'M&A'!$A:$A,$A8,'M&A'!$L:$L,D$3)+SUMIFS(Raises!$F:$F,Raises!$A:$A,$A8,Raises!$L:$L,D$3) | E8: =SUMIFS('M&A'!$G:$G,'M&A'!$A:$A,$A8,'M&A'!$L:$L,E$3)+SUMIFS(Raises!$F:$F,Raises!$A:$A,$A8,Raises!$L:$L,E$3)
A9: InsurTech | B9: =SUMIFS('M&A'!$G:$G,'M&A'!$A:$A,$A9,'M&A'!$L:$L,B$3)+SUMIFS(Raises!$F:$F,Raises!$A:$A,$A9,Raises!$L:$L,B$3) | C9: =SUMIFS('M&A'!$G:$G,'M&A'!$A:$A,$A9,'M&A'!$L:$L,C$3)+SUMIFS(Raises!$F:$F,Raises!$A:$A,$A9,Raises!$L:$L,C$3) | D9: =SUMIFS('M&A'!$G:$G,'M&A'!$A:$A,$A9,'M&A'!$L:$L,D$3)+SUMIFS(Raises!$F:$F,Raises!$A:$A,$A9,Raises!$L:$L,D$3) | E9: =SUMIFS('M&A'!$G:$G,'M&A'!$A:$A,$A9,'M&A'!$L:$L,E$3)+SUMIFS(Raises!$F:$F,Raises!$A:$A,$A9,Raises!$L:$L,E$3)
A10: Payments | B10: =SUMIFS('M&A'!$G:$G,'M&A'!$A:$A,$A10,'M&A'!$L:$L,B$3)+SUMIFS(Raises!$F:$F,Raises!$A:$A,$A10,Raises!$L:$L,B$3) | C10: =SUMIFS('M&A'!$G:$G,'M&A'!$A:$A,$A10,'M&A'!$L:$L,C$3)+SUMIFS(Raises!$F:$F,Raises!$A:$A,$A10,Raises!$L:$L,C$3) | D10: =SUMIFS('M&A'!$G:$G,'M&A'!$A:$A,$A10,'M&A'!$L:$L,D$3)+SUMIFS(Raises!$F:$F,Raises!$A:$A,$A10,Raises!$L:$L,D$3) | E10: =SUMIFS('M&A'!$G:$G,'M&A'!$A:$A,$A10,'M&A'!$L:$L,E$3)+SUMIFS(Raises!$F:$F,Raises!$A:$A,$A10,Raises!$L:$L,E$3)
A11: Real Estate & Mortgage Tech | B11: =SUMIFS('M&A'!$G:$G,'M&A'!$A:$A,$A11,'M&A'!$L:$L,B$3)+SUMIFS(Raises!$F:$F,Raises!$A:$A,$A11,Raises!$L:$L,B$3) | C11: =SUMIFS('M&A'!$G:$G,'M&A'!$A:$A,$A11,'M&A'!$L:$L,C$3)+SUMIFS(Raises!$F:$F,Raises!$A:$A,$A11,Raises!$L:$L,C$3) | D11: =SUMIFS('M&A'!$G:$G,'M&A'!$A:$A,$A11,'M&A'!$L:$L,D$3)+SUMIFS(Raises!$F:$F,Raises!$A:$A,$A11,Raises!$L:$L,D$3) | E11: =SUMIFS('M&A'!$G:$G,'M&A'!$A:$A,$A11,'M&A'!$L:$L,E$3)+SUMIFS(Raises!$F:$F,Raises!$A:$A,$A11,Raises!$L:$L,E$3)
A14: # OF DEALS
A15: Subsector (#) | B15: 2025-Q3 | C15: 2025-Q4 | D15: 2026-Q1 | E15: 2026-Q2
A16: Asset & Wealth Tech | B16: =COUNTIFS('M&A'!$A:$A,$A16,'M&A'!$L:$L,B$15)+COUNTIFS(Raises!$A:$A,$A16,Raises!$L:$L,B$15) | C16: =COUNTIFS('M&A'!$A:$A,$A16,'M&A'!$L:$L,C$15)+COUNTIFS(Raises!$A:$A,$A16,Raises!$L:$L,C$15) | D16: =COUNTIFS('M&A'!$A:$A,$A16,'M&A'!$L:$L,D$15)+COUNTIFS(Raises!$A:$A,$A16,Raises!$L:$L,D$15) | E16: =COUNTIFS('M&A'!$A:$A,$A16,'M&A'!$L:$L,E$15)+COUNTIFS(Raises!$A:$A,$A16,Raises!$L:$L,E$15)
A17: Banking & Lending Tech | B17: =COUNTIFS('M&A'!$A:$A,$A17,'M&A'!$L:$L,B$15)+COUNTIFS(Raises!$A:$A,$A17,Raises!$L:$L,B$15) | C17: =COUNTIFS('M&A'!$A:$A,$A17,'M&A'!$L:$L,C$15)+COUNTIFS(Raises!$A:$A,$A17,Raises!$L:$L,C$15) | D17: =COUNTIFS('M&A'!$A:$A,$A17,'M&A'!$L:$L,D$15)+COUNTIFS(Raises!$A:$A,$A17,Raises!$L:$L,D$15) | E17: =COUNTIFS('M&A'!$A:$A,$A17,'M&A'!$L:$L,E$15)+COUNTIFS(Raises!$A:$A,$A17,Raises!$L:$L,E$15)
A18: Capital Markets Tech | B18: =COUNTIFS('M&A'!$A:$A,$A18,'M&A'!$L:$L,B$15)+COUNTIFS(Raises!$A:$A,$A18,Raises!$L:$L,B$15) | C18: =COUNTIFS('M&A'!$A:$A,$A18,'M&A'!$L:$L,C$15)+COUNTIFS(Raises!$A:$A,$A18,Raises!$L:$L,C$15) | D18: =COUNTIFS('M&A'!$A:$A,$A18,'M&A'!$L:$L,D$15)+COUNTIFS(Raises!$A:$A,$A18,Raises!$L:$L,D$15) | E18: =COUNTIFS('M&A'!$A:$A,$A18,'M&A'!$L:$L,E$15)+COUNTIFS(Raises!$A:$A,$A18,Raises!$L:$L,E$15)
A19: Corporate Financial Function | B19: =COUNTIFS('M&A'!$A:$A,$A19,'M&A'!$L:$L,B$15)+COUNTIFS(Raises!$A:$A,$A19,Raises!$L:$L,B$15) | C19: =COUNTIFS('M&A'!$A:$A,$A19,'M&A'!$L:$L,C$15)+COUNTIFS(Raises!$A:$A,$A19,Raises!$L:$L,C$15) | D19: =COUNTIFS('M&A'!$A:$A,$A19,'M&A'!$L:$L,D$15)+COUNTIFS(Raises!$A:$A,$A19,Raises!$L:$L,D$15) | E19: =COUNTIFS('M&A'!$A:$A,$A19,'M&A'!$L:$L,E$15)+COUNTIFS(Raises!$A:$A,$A19,Raises!$L:$L,E$15)
A20: Financial Info & Analytics | B20: =COUNTIFS('M&A'!$A:$A,$A20,'M&A'!$L:$L,B$15)+COUNTIFS(Raises!$A:$A,$A20,Raises!$L:$L,B$15) | C20: =COUNTIFS('M&A'!$A:$A,$A20,'M&A'!$L:$L,C$15)+COUNTIFS(Raises!$A:$A,$A20,Raises!$L:$L,C$15) | D20: =COUNTIFS('M&A'!$A:$A,$A20,'M&A'!$L:$L,D$15)+COUNTIFS(Raises!$A:$A,$A20,Raises!$L:$L,D$15) | E20: =COUNTIFS('M&A'!$A:$A,$A20,'M&A'!$L:$L,E$15)+COUNTIFS(Raises!$A:$A,$A20,Raises!$L:$L,E$15)
A21: InsurTech | B21: =COUNTIFS('M&A'!$A:$A,$A21,'M&A'!$L:$L,B$15)+COUNTIFS(Raises!$A:$A,$A21,Raises!$L:$L,B$15) | C21: =COUNTIFS('M&A'!$A:$A,$A21,'M&A'!$L:$L,C$15)+COUNTIFS(Raises!$A:$A,$A21,Raises!$L:$L,C$15) | D21: =COUNTIFS('M&A'!$A:$A,$A21,'M&A'!$L:$L,D$15)+COUNTIFS(Raises!$A:$A,$A21,Raises!$L:$L,D$15) | E21: =COUNTIFS('M&A'!$A:$A,$A21,'M&A'!$L:$L,E$15)+COUNTIFS(Raises!$A:$A,$A21,Raises!$L:$L,E$15)
A22: Payments | B22: =COUNTIFS('M&A'!$A:$A,$A22,'M&A'!$L:$L,B$15)+COUNTIFS(Raises!$A:$A,$A22,Raises!$L:$L,B$15) | C22: =COUNTIFS('M&A'!$A:$A,$A22,'M&A'!$L:$L,C$15)+COUNTIFS(Raises!$A:$A,$A22,Raises!$L:$L,C$15) | D22: =COUNTIFS('M&A'!$A:$A,$A22,'M&A'!$L:$L,D$15)+COUNTIFS(Raises!$A:$A,$A22,Raises!$L:$L,D$15) | E22: =COUNTIFS('M&A'!$A:$A,$A22,'M&A'!$L:$L,E$15)+COUNTIFS(Raises!$A:$A,$A22,Raises!$L:$L,E$15)
A23: Real Estate & Mortgage Tech | B23: =COUNTIFS('M&A'!$A:$A,$A23,'M&A'!$L:$L,B$15)+COUNTIFS(Raises!$A:$A,$A23,Raises!$L:$L,B$15) | C23: =COUNTIFS('M&A'!$A:$A,$A23,'M&A'!$L:$L,C$15)+COUNTIFS(Raises!$A:$A,$A23,Raises!$L:$L,C$15) | D23: =COUNTIFS('M&A'!$A:$A,$A23,'M&A'!$L:$L,D$15)+COUNTIFS(Raises!$A:$A,$A23,Raises!$L:$L,D$15) | E23: =COUNTIFS('M&A'!$A:$A,$A23,'M&A'!$L:$L,E$15)+COUNTIFS(Raises!$A:$A,$A23,Raises!$L:$L,E$15)

Sheet Subsector Map
A1: Ticker | B1: Subsector
A2: LSE:AMIF | B2: Asset & Wealth Tech
A3: ASX:CPU | B3: Asset & Wealth Tech
A4: NYSE:DFIN | B4: Asset & Wealth Tech
A5: LSE:JTC | B5: Asset & Wealth Tech
A6: NSEI:KFINTECH | B6: Asset & Wealth Tech
A7: NASDAQ:SSNC | B7: Asset & Wealth Tech
A8: LSE:XPS | B8: Asset & Wealth Tech
A9: ENXTAM:ALLFG | B9: Asset & Wealth Tech
A10: NASDAQ:BENF | B10: Asset & Wealth Tech
A11: LSE:IHP | B11: Asset & Wealth Tech
A12: ASX:BVS | B12: Asset & Wealth Tech
... A294: NYSE:NP | B294: InsurTech

Sheet Comps
A1: As-Of Date | B1: Display Name | C1: Ticker | D1: Market Cap | E1: Total Cash | F1: Total Debt | G1: Minority Interests | H1: Manual Adjustments | I1: Net Debt | J1: Enterprise Value | K1: Current Price | L1: YTD Return | M1: 1-Yr Return | N1: % 52wk High | O1: Rev CY2022 | P1: Rev CY2023 | Q1: Rev CY2024 | R1: Rev CY2025 | S1: Rev CY2026 | T1: Rev CY2027 | U1: EBITDA CY2022 | V1: EBITDA CY2023 | W1: EBITDA CY2024 | X1: EBITDA CY2025 | Y1: EBITDA CY2026 | Z1: EBITDA CY2027 | AA1: FCF CY2022 | AB1: FCF CY2023 | AC1: FCF CY2024 | AD1: FCF CY2025 | AE1: FCF CY2026 | AF1: FCF CY2027 | AG1: EV/Rev CY2025 | AH1: EV/Rev CY2026 | AI1: EV/Rev CY2027 | AJ1: EV/EBITDA CY2025 | AK1: EV/EBITDA CY2026 | AL1: EV/EBITDA CY2027 | AM1: YoY RevGr26 | AN1: YoY EBITDAGr26 | AO1: EBITDA Mgn26 | AP1: FCF Mgn26 | AQ1: Rule40 26 | AR1: YoY RevGr27 | AS1: YoY EBITDAGr27 | AT1: EBITDA Mgn27 | AU1: FCF Mgn27 | AV1: Rule40 27 | AW1: GrossMgn25 | AX1: GrossMgn26 | AY1: Subsector | AZ1: FwdRev(CY+1) | BA1: Fwd EV/Rev | BB1: FwdEBITDA(CY+1) | BC1: Fwd EV/EBITDA
AY2: =IFERROR(VLOOKUP(C2,'Subsector Map'!$A:$B,2,0),"") | AZ2: =IFERROR(INDEX(O2:T2,MATCH(YEAR(A2)+1,{2022,2023,2024,2025,2026,2027},0)),"") | BA2: =IFERROR(J2/AZ2,"") | BB2: =IFERROR(INDEX(U2:Z2,MATCH(YEAR(A2)+1,{2022,2023,2024,2025,2026,2027},0)),"") | BC2: =IFERROR(J2/BB2,"")
AY3: =IFERROR(VLOOKUP(C3,'Subsector Map'!$A:$B,2,0),"") | AZ3: =IFERROR(INDEX(O3:T3,MATCH(YEAR(A3)+1,{2022,2023,2024,2025,2026,2027},0)),"") | BA3: =IFERROR(J3/AZ3,"") | BB3: =IFERROR(INDEX(U3:Z3,MATCH(YEAR(A3)+1,{2022,2023,2024,2025,2026,2027},0)),"") | BC3: =IFERROR(J3/BB3,"")
AY4: =IFERROR(VLOOKUP(C4,'Subsector Map'!$A:$B,2,0),"") | AZ4: =IFERROR(INDEX(O4:T4,MATCH(YEAR(A4)+1,{2022,2023,2024,2025,2026,2027},0)),"") | BA4: =IFERROR(J4/AZ4,"") | BB4: =IFERROR(INDEX(U4:Z4,MATCH(YEAR(A4)+1,{2022,2023,2024,2025,2026,2027},0)),"") | BC4: =IFERROR(J4/BB4,"")
AY5: =IFERROR(VLOOKUP(C5,'Subsector Map'!$A:$B,2,0),"") | AZ5: =IFERROR(INDEX(O5:T5,MATCH(YEAR(A5)+1,{2022,2023,2024,2025,2026,2027},0)),"") | BA5: =IFERROR(J5/AZ5,"") | BB5: =IFERROR(INDEX(U5:Z5,MATCH(YEAR(A5)+1,{2022,2023,2024,2025,2026,2027},0)),"") | BC5: =IFERROR(J5/BB5,"")
AY6: =IFERROR(VLOOKUP(C6,'Subsector Map'!$A:$B,2,0),"") | AZ6: =IFERROR(INDEX(O6:T6,MATCH(YEAR(A6)+1,{2022,2023,2024,2025,2026,2027},0)),"") | BA6: =IFERROR(J6/AZ6,"") | BB6: =IFERROR(INDEX(U6:Z6,MATCH(YEAR(A6)+1,{2022,2023,2024,2025,2026,2027},0)),"") | BC6: =IFERROR(J6/BB6,"")
AY7: =IFERROR(VLOOKUP(C7,'Subsector Map'!$A:$B,2,0),"") | AZ7: =IFERROR(INDEX(O7:T7,MATCH(YEAR(A7)+1,{2022,2023,2024,2025,2026,2027},0)),"") | BA7: =IFERROR(J7/AZ7,"") | BB7: =IFERROR(INDEX(U7:Z7,MATCH(YEAR(A7)+1,{2022,2023,2024,2025,2026,2027},0)),"") | BC7: =IFERROR(J7/BB7,"")
AY8: =IFERROR(VLOOKUP(C8,'Subsector Map'!$A:$B,2,0),"") | AZ8: =IFERROR(INDEX(O8:T8,MATCH(YEAR(A8)+1,{2022,2023,2024,2025,2026,2027},0)),"") | BA8: =IFERROR(J8/AZ8,"") | BB8: =IFERROR(INDEX(U8:Z8,MATCH(YEAR(A8)+1,{2022,2023,2024,2025,2026,2027},0)),"") | BC8: =IFERROR(J8/BB8,"")
AY9: =IFERROR(VLOOKUP(C9,'Subsector Map'!$A:$B,2,0),"") | AZ9: =IFERROR(INDEX(O9:T9,MATCH(YEAR(A9)+1,{2022,2023,2024,2025,2026,2027},0)),"") | BA9: =IFERROR(J9/AZ9,"") | BB9: =IFERROR(INDEX(U9:Z9,MATCH(YEAR(A9)+1,{2022,2023,2024,2025,2026,2027},0)),"") | BC9: =IFERROR(J9/BB9,"")
AY10: =IFERROR(VLOOKUP(C10,'Subsector Map'!$A:$B,2,0),"") | AZ10: =IFERROR(INDEX(O10:T10,MATCH(YEAR(A10)+1,{2022,2023,2024,2025,2026,2027},0)),"") | BA10: =IFERROR(J10/AZ10,"") | BB10: =IFERROR(INDEX(U10:Z10,MATCH(YEAR(A10)+1,{2022,2023,2024,2025,2026,2027},0)),"") | BC10: =IFERROR(J10/BB10,"")
AY11: =IFERROR(VLOOKUP(C11,'Subsector Map'!$A:$B,2,0),"") | AZ11: =IFERROR(INDEX(O11:T11,MATCH(YEAR(A11)+1,{2022,2023,2024,2025,2026,2027},0)),"") | BA11: =IFERROR(J11/AZ11,"") | BB11: =IFERROR(INDEX(U11:Z11,MATCH(YEAR(A11)+1,{2022,2023,2024,2025,2026,2027},0)),"") | BC11: =IFERROR(J11/BB11,"")
AY12: =IFERROR(VLOOKUP(C12,'Subsector Map'!$A:$B,2,0),"") | AZ12: =IFERROR(INDEX(O12:T12,MATCH(YEAR(A12)+1,{2022,2023,2024,2025,2026,2027},0)),"") | BA12: =IFERROR(J12/AZ12,"") | BB12: =IFERROR(INDEX(U12:Z12,MATCH(YEAR(A12)+1,{2022,2023,2024,2025,2026,2027},0)),"") | BC12: =IFERROR(J12/BB12,"")
AY13: =IFERROR(VLOOKUP(C13,'Subsector Map'!$A:$B,2,0),"") | AZ13: =IFERROR(INDEX(O13:T13,MATCH(YEAR(A13)+1,{2022,2023,2024,2025,2026,2027},0)),"") | BA13: =IFERROR(J13/AZ13,"") | BB13: =IFERROR(INDEX(U13:Z13,MATCH(YEAR(A13)+1,{2022,2023,2024,2025,2026,2027},0)),"") | BC13: =IFERROR(J13/BB13,"")
... AY5000: =IFERROR(VLOOKUP(C5000,'Subsector Map'!$A:$B,2,0),"") | AZ5000: =IFERROR(INDEX(O5000:T5000,MATCH(YEAR(A5000)+1,{2022,2023,2024,2025,2026,2027},0)),"") | BA5000: =IFERROR(J5000/AZ5000,"") | BB5000: =IFERROR(INDEX(U5000:Z5000,MATCH(YEAR(A5000)+1,{2022,2023,2024,2025,2026,2027},0)),"") | BC5000: =IFERROR(J5000/BB5000,"")

Sheet Multiples
A1: PUBLIC FORWARD EV/REVENUE — median by subsector by snapshot
A2: Put your snapshot As-Of dates in B4, C4, ... (match the dates you stamped in Comps col A).
A4: Subsector \ As-Of | B4: (date1) | C4: (date2) | D4: (date3) | E4: (date4)
A5: Asset & Wealth Tech | B5: =IFERROR(MEDIAN(IF((Comps!$BA$2:$BA$5000<>"")*(Comps!$AY$2:$AY$5000=$A5)*(Comps!$A$2:$A$5000=B$4),Comps!$BA$2:$BA$5000)),"") | C5: =IFERROR(MEDIAN(IF((Comps!$BA$2:$BA$5000<>"")*(Comps!$AY$2:$AY$5000=$A5)*(Comps!$A$2:$A$5000=C$4),Comps!$BA$2:$BA$5000)),"") | D5: =IFERROR(MEDIAN(IF((Comps!$BA$2:$BA$5000<>"")*(Comps!$AY$2:$AY$5000=$A5)*(Comps!$A$2:$A$5000=D$4),Comps!$BA$2:$BA$5000)),"") | E5: =IFERROR(MEDIAN(IF((Comps!$BA$2:$BA$5000<>"")*(Comps!$AY$2:$AY$5000=$A5)*(Comps!$A$2:$A$5000=E$4),Comps!$BA$2:$BA$5000)),"")
A6: Banking & Lending Tech | B6: =IFERROR(MEDIAN(IF((Comps!$BA$2:$BA$5000<>"")*(Comps!$AY$2:$AY$5000=$A6)*(Comps!$A$2:$A$5000=B$4),Comps!$BA$2:$BA$5000)),"") | C6: =IFERROR(MEDIAN(IF((Comps!$BA$2:$BA$5000<>"")*(Comps!$AY$2:$AY$5000=$A6)*(Comps!$A$2:$A$5000=C$4),Comps!$BA$2:$BA$5000)),"") | D6: =IFERROR(MEDIAN(IF((Comps!$BA$2:$BA$5000<>"")*(Comps!$AY$2:$AY$5000=$A6)*(Comps!$A$2:$A$5000=D$4),Comps!$BA$2:$BA$5000)),"") | E6: =IFERROR(MEDIAN(IF((Comps!$BA$2:$BA$5000<>"")*(Comps!$AY$2:$AY$5000=$A6)*(Comps!$A$2:$A$5000=E$4),Comps!$BA$2:$BA$5000)),"")
A7: Capital Markets Tech | B7: =IFERROR(MEDIAN(IF((Comps!$BA$2:$BA$5000<>"")*(Comps!$AY$2:$AY$5000=$A7)*(Comps!$A$2:$A$5000=B$4),Comps!$BA$2:$BA$5000)),"") | C7: =IFERROR(MEDIAN(IF((Comps!$BA$2:$BA$5000<>"")*(Comps!$AY$2:$AY$5000=$A7)*(Comps!$A$2:$A$5000=C$4),Comps!$BA$2:$BA$5000)),"") | D7: =IFERROR(MEDIAN(IF((Comps!$BA$2:$BA$5000<>"")*(Comps!$AY$2:$AY$5000=$A7)*(Comps!$A$2:$A$5000=D$4),Comps!$BA$2:$BA$5000)),"") | E7: =IFERROR(MEDIAN(IF((Comps!$BA$2:$BA$5000<>"")*(Comps!$AY$2:$AY$5000=$A7)*(Comps!$A$2:$A$5000=E$4),Comps!$BA$2:$BA$5000)),"")
A8: Corporate Financial Function | B8: =IFERROR(MEDIAN(IF((Comps!$BA$2:$BA$5000<>"")*(Comps!$AY$2:$AY$5000=$A8)*(Comps!$A$2:$A$5000=B$4),Comps!$BA$2:$BA$5000)),"") | C8: =IFERROR(MEDIAN(IF((Comps!$BA$2:$BA$5000<>"")*(Comps!$AY$2:$AY$5000=$A8)*(Comps!$A$2:$A$5000=C$4),Comps!$BA$2:$BA$5000)),"") | D8: =IFERROR(MEDIAN(IF((Comps!$BA$2:$BA$5000<>"")*(Comps!$AY$2:$AY$5000=$A8)*(Comps!$A$2:$A$5000=D$4),Comps!$BA$2:$BA$5000)),"") | E8: =IFERROR(MEDIAN(IF((Comps!$BA$2:$BA$5000<>"")*(Comps!$AY$2:$AY$5000=$A8)*(Comps!$A$2:$A$5000=E$4),Comps!$BA$2:$BA$5000)),"")
A9: Financial Info & Analytics | B9: =IFERROR(MEDIAN(IF((Comps!$BA$2:$BA$5000<>"")*(Comps!$AY$2:$AY$5000=$A9)*(Comps!$A$2:$A$5000=B$4),Comps!$BA$2:$BA$5000)),"") | C9: =IFERROR(MEDIAN(IF((Comps!$BA$2:$BA$5000<>"")*(Comps!$AY$2:$AY$5000=$A9)*(Comps!$A$2:$A$5000=C$4),Comps!$BA$2:$BA$5000)),"") | D9: =IFERROR(MEDIAN(IF((Comps!$BA$2:$BA$5000<>"")*(Comps!$AY$2:$AY$5000=$A9)*(Comps!$A$2:$A$5000=D$4),Comps!$BA$2:$BA$5000)),"") | E9: =IFERROR(MEDIAN(IF((Comps!$BA$2:$BA$5000<>"")*(Comps!$AY$2:$AY$5000=$A9)*(Comps!$A$2:$A$5000=E$4),Comps!$BA$2:$BA$5000)),"")
A10: InsurTech | B10: =IFERROR(MEDIAN(IF((Comps!$BA$2:$BA$5000<>"")*(Comps!$AY$2:$AY$5000=$A10)*(Comps!$A$2:$A$5000=B$4),Comps!$BA$2:$BA$5000)),"") | C10: =IFERROR(MEDIAN(IF((Comps!$BA$2:$BA$5000<>"")*(Comps!$AY$2:$AY$5000=$A10)*(Comps!$A$2:$A$5000=C$4),Comps!$BA$2:$BA$5000)),"") | D10: =IFERROR(MEDIAN(IF((Comps!$BA$2:$BA$5000<>"")*(Comps!$AY$2:$AY$5000=$A10)*(Comps!$A$2:$A$5000=D$4),Comps!$BA$2:$BA$5000)),"") | E10: =IFERROR(MEDIAN(IF((Comps!$BA$2:$BA$5000<>"")*(Comps!$AY$2:$AY$5000=$A10)*(Comps!$A$2:$A$5000=E$4),Comps!$BA$2:$BA$5000)),"")
A11: Payments | B11: =IFERROR(MEDIAN(IF((Comps!$BA$2:$BA$5000<>"")*(Comps!$AY$2:$AY$5000=$A11)*(Comps!$A$2:$A$5000=B$4),Comps!$BA$2:$BA$5000)),"") | C11: =IFERROR(MEDIAN(IF((Comps!$BA$2:$BA$5000<>"")*(Comps!$AY$2:$AY$5000=$A11)*(Comps!$A$2:$A$5000=C$4),Comps!$BA$2:$BA$5000)),"") | D11: =IFERROR(MEDIAN(IF((Comps!$BA$2:$BA$5000<>"")*(Comps!$AY$2:$AY$5000=$A11)*(Comps!$A$2:$A$5000=D$4),Comps!$BA$2:$BA$5000)),"") | E11: =IFERROR(MEDIAN(IF((Comps!$BA$2:$BA$5000<>"")*(Comps!$AY$2:$AY$5000=$A11)*(Comps!$A$2:$A$5000=E$4),Comps!$BA$2:$BA$5000)),"")
A12: Real Estate & Mortgage Tech | B12: =IFERROR(MEDIAN(IF((Comps!$BA$2:$BA$5000<>"")*(Comps!$AY$2:$AY$5000=$A12)*(Comps!$A$2:$A$5000=B$4),Comps!$BA$2:$BA$5000)),"") | C12: =IFERROR(MEDIAN(IF((Comps!$BA$2:$BA$5000<>"")*(Comps!$AY$2:$AY$5000=$A12)*(Comps!$A$2:$A$5000=C$4),Comps!$BA$2:$BA$5000)),"") | D12: =IFERROR(MEDIAN(IF((Comps!$BA$2:$BA$5000<>"")*(Comps!$AY$2:$AY$5000=$A12)*(Comps!$A$2:$A$5000=D$4),Comps!$BA$2:$BA$5000)),"") | E12: =IFERROR(MEDIAN(IF((Comps!$BA$2:$BA$5000<>"")*(Comps!$AY$2:$AY$5000=$A12)*(Comps!$A$2:$A$5000=E$4),Comps!$BA$2:$BA$5000)),"")
A15: PRIVATE EV/REVENUE — median by subsector by deal year (from M&A + Raises, where disclosed)
A16: Subsector \ Year | B16: 2024 | C16: 2025 | D16: 2026
A17: Asset & Wealth Tech | B17: =IFERROR(MEDIAN(IF(('M&A'!$A$2:$A$1000=$A17)*(YEAR('M&A'!$D$2:$D$1000)=B$16)*('M&A'!$H$2:$H$1000<>""),'M&A'!$H$2:$H$1000),IF((Raises!$A$2:$A$1000=$A17)*(YEAR(Raises!$C$2:$C$1000)=B$16)*(Raises!$H$2:$H$1000<>""),Raises!$H$2:$H$1000)),"") | C17: =IFERROR(MEDIAN(IF(('M&A'!$A$2:$A$1000=$A17)*(YEAR('M&A'!$D$2:$D$1000)=C$16)*('M&A'!$H$2:$H$1000<>""),'M&A'!$H$2:$H$1000),IF((Raises!$A$2:$A$1000=$A17)*(YEAR(Raises!$C$2:$C$1000)=C$16)*(Raises!$H$2:$H$1000<>""),Raises!$H$2:$H$1000)),"") | D17: =IFERROR(MEDIAN(IF(('M&A'!$A$2:$A$1000=$A17)*(YEAR('M&A'!$D$2:$D$1000)=D$16)*('M&A'!$H$2:$H$1000<>""),'M&A'!$H$2:$H$1000),IF((Raises!$A$2:$A$1000=$A17)*(YEAR(Raises!$C$2:$C$1000)=D$16)*(Raises!$H$2:$H$1000<>""),Raises!$H$2:$H$1000)),"")
A18: Banking & Lending Tech | B18: =IFERROR(MEDIAN(IF(('M&A'!$A$2:$A$1000=$A18)*(YEAR('M&A'!$D$2:$D$1000)=B$16)*('M&A'!$H$2:$H$1000<>""),'M&A'!$H$2:$H$1000),IF((Raises!$A$2:$A$1000=$A18)*(YEAR(Raises!$C$2:$C$1000)=B$16)*(Raises!$H$2:$H$1000<>""),Raises!$H$2:$H$1000)),"") | C18: =IFERROR(MEDIAN(IF(('M&A'!$A$2:$A$1000=$A18)*(YEAR('M&A'!$D$2:$D$1000)=C$16)*('M&A'!$H$2:$H$1000<>""),'M&A'!$H$2:$H$1000),IF((Raises!$A$2:$A$1000=$A18)*(YEAR(Raises!$C$2:$C$1000)=C$16)*(Raises!$H$2:$H$1000<>""),Raises!$H$2:$H$1000)),"") | D18: =IFERROR(MEDIAN(IF(('M&A'!$A$2:$A$1000=$A18)*(YEAR('M&A'!$D$2:$D$1000)=D$16)*('M&A'!$H$2:$H$1000<>""),'M&A'!$H$2:$H$1000),IF((Raises!$A$2:$A$1000=$A18)*(YEAR(Raises!$C$2:$C$1000)=D$16)*(Raises!$H$2:$H$1000<>""),Raises!$H$2:$H$1000)),"")
A19: Capital Markets Tech | B19: =IFERROR(MEDIAN(IF(('M&A'!$A$2:$A$1000=$A19)*(YEAR('M&A'!$D$2:$D$1000)=B$16)*('M&A'!$H$2:$H$1000<>""),'M&A'!$H$2:$H$1000),IF((Raises!$A$2:$A$1000=$A19)*(YEAR(Raises!$C$2:$C$1000)=B$16)*(Raises!$H$2:$H$1000<>""),Raises!$H$2:$H$1000)),"") | C19: =IFERROR(MEDIAN(IF(('M&A'!$A$2:$A$1000=$A19)*(YEAR('M&A'!$D$2:$D$1000)=C$16)*('M&A'!$H$2:$H$1000<>""),'M&A'!$H$2:$H$1000),IF((Raises!$A$2:$A$1000=$A19)*(YEAR(Raises!$C$2:$C$1000)=C$16)*(Raises!$H$2:$H$1000<>""),Raises!$H$2:$H$1000)),"") | D19: =IFERROR(MEDIAN(IF(('M&A'!$A$2:$A$1000=$A19)*(YEAR('M&A'!$D$2:$D$1000)=D$16)*('M&A'!$H$2:$H$1000<>""),'M&A'!$H$2:$H$1000),IF((Raises!$A$2:$A$1000=$A19)*(YEAR(Raises!$C$2:$C$1000)=D$16)*(Raises!$H$2:$H$1000<>""),Raises!$H$2:$H$1000)),"")
A20: Corporate Financial Function | B20: =IFERROR(MEDIAN(IF(('M&A'!$A$2:$A$1000=$A20)*(YEAR('M&A'!$D$2:$D$1000)=B$16)*('M&A'!$H$2:$H$1000<>""),'M&A'!$H$2:$H$1000),IF((Raises!$A$2:$A$1000=$A20)*(YEAR(Raises!$C$2:$C$1000)=B$16)*(Raises!$H$2:$H$1000<>""),Raises!$H$2:$H$1000)),"") | C20: =IFERROR(MEDIAN(IF(('M&A'!$A$2:$A$1000=$A20)*(YEAR('M&A'!$D$2:$D$1000)=C$16)*('M&A'!$H$2:$H$1000<>""),'M&A'!$H$2:$H$1000),IF((Raises!$A$2:$A$1000=$A20)*(YEAR(Raises!$C$2:$C$1000)=C$16)*(Raises!$H$2:$H$1000<>""),Raises!$H$2:$H$1000)),"") | D20: =IFERROR(MEDIAN(IF(('M&A'!$A$2:$A$1000=$A20)*(YEAR('M&A'!$D$2:$D$1000)=D$16)*('M&A'!$H$2:$H$1000<>""),'M&A'!$H$2:$H$1000),IF((Raises!$A$2:$A$1000=$A20)*(YEAR(Raises!$C$2:$C$1000)=D$16)*(Raises!$H$2:$H$1000<>""),Raises!$H$2:$H$1000)),"")
A21: Financial Info & Analytics | B21: =IFERROR(MEDIAN(IF(('M&A'!$A$2:$A$1000=$A21)*(YEAR('M&A'!$D$2:$D$1000)=B$16)*('M&A'!$H$2:$H$1000<>""),'M&A'!$H$2:$H$1000),IF((Raises!$A$2:$A$1000=$A21)*(YEAR(Raises!$C$2:$C$1000)=B$16)*(Raises!$H$2:$H$1000<>""),Raises!$H$2:$H$1000)),"") | C21: =IFERROR(MEDIAN(IF(('M&A'!$A$2:$A$1000=$A21)*(YEAR('M&A'!$D$2:$D$1000)=C$16)*('M&A'!$H$2:$H$1000<>""),'M&A'!$H$2:$H$1000),IF((Raises!$A$2:$A$1000=$A21)*(YEAR(Raises!$C$2:$C$1000)=C$16)*(Raises!$H$2:$H$1000<>""),Raises!$H$2:$H$1000)),"") | D21: =IFERROR(MEDIAN(IF(('M&A'!$A$2:$A$1000=$A21)*(YEAR('M&A'!$D$2:$D$1000)=D$16)*('M&A'!$H$2:$H$1000<>""),'M&A'!$H$2:$H$1000),IF((Raises!$A$2:$A$1000=$A21)*(YEAR(Raises!$C$2:$C$1000)=D$16)*(Raises!$H$2:$H$1000<>""),Raises!$H$2:$H$1000)),"")
A22: InsurTech | B22: =IFERROR(MEDIAN(IF(('M&A'!$A$2:$A$1000=$A22)*(YEAR('M&A'!$D$2:$D$1000)=B$16)*('M&A'!$H$2:$H$1000<>""),'M&A'!$H$2:$H$1000),IF((Raises!$A$2:$A$1000=$A22)*(YEAR(Raises!$C$2:$C$1000)=B$16)*(Raises!$H$2:$H$1000<>""),Raises!$H$2:$H$1000)),"") | C22: =IFERROR(MEDIAN(IF(('M&A'!$A$2:$A$1000=$A22)*(YEAR('M&A'!$D$2:$D$1000)=C$16)*('M&A'!$H$2:$H$1000<>""),'M&A'!$H$2:$H$1000),IF((Raises!$A$2:$A$1000=$A22)*(YEAR(Raises!$C$2:$C$1000)=C$16)*(Raises!$H$2:$H$1000<>""),Raises!$H$2:$H$1000)),"") | D22: =IFERROR(MEDIAN(IF(('M&A'!$A$2:$A$1000=$A22)*(YEAR('M&A'!$D$2:$D$1000)=D$16)*('M&A'!$H$2:$H$1000<>""),'M&A'!$H$2:$H$1000),IF((Raises!$A$2:$A$1000=$A22)*(YEAR(Raises!$C$2:$C$1000)=D$16)*(Raises!$H$2:$H$1000<>""),Raises!$H$2:$H$1000)),"")
A23: Payments | B23: =IFERROR(MEDIAN(IF(('M&A'!$A$2:$A$1000=$A23)*(YEAR('M&A'!$D$2:$D$1000)=B$16)*('M&A'!$H$2:$H$1000<>""),'M&A'!$H$2:$H$1000),IF((Raises!$A$2:$A$1000=$A23)*(YEAR(Raises!$C$2:$C$1000)=B$16)*(Raises!$H$2:$H$1000<>""),Raises!$H$2:$H$1000)),"") | C23: =IFERROR(MEDIAN(IF(('M&A'!$A$2:$A$1000=$A23)*(YEAR('M&A'!$D$2:$D$1000)=C$16)*('M&A'!$H$2:$H$1000<>""),'M&A'!$H$2:$H$1000),IF((Raises!$A$2:$A$1000=$A23)*(YEAR(Raises!$C$2:$C$1000)=C$16)*(Raises!$H$2:$H$1000<>""),Raises!$H$2:$H$1000)),"") | D23: =IFERROR(MEDIAN(IF(('M&A'!$A$2:$A$1000=$A23)*(YEAR('M&A'!$D$2:$D$1000)=D$16)*('M&A'!$H$2:$H$1000<>""),'M&A'!$H$2:$H$1000),IF((Raises!$A$2:$A$1000=$A23)*(YEAR(Raises!$C$2:$C$1000)=D$16)*(Raises!$H$2:$H$1000<>""),Raises!$H$2:$H$1000)),"")
A24: Real Estate & Mortgage Tech | B24: =IFERROR(MEDIAN(IF(('M&A'!$A$2:$A$1000=$A24)*(YEAR('M&A'!$D$2:$D$1000)=B$16)*('M&A'!$H$2:$H$1000<>""),'M&A'!$H$2:$H$1000),IF((Raises!$A$2:$A$1000=$A24)*(YEAR(Raises!$C$2:$C$1000)=B$16)*(Raises!$H$2:$H$1000<>""),Raises!$H$2:$H$1000)),"") | C24: =IFERROR(MEDIAN(IF(('M&A'!$A$2:$A$1000=$A24)*(YEAR('M&A'!$D$2:$D$1000)=C$16)*('M&A'!$H$2:$H$1000<>""),'M&A'!$H$2:$H$1000),IF((Raises!$A$2:$A$1000=$A24)*(YEAR(Raises!$C$2:$C$1000)=C$16)*(Raises!$H$2:$H$1000<>""),Raises!$H$2:$H$1000)),"") | D24: =IFERROR(MEDIAN(IF(('M&A'!$A$2:$A$1000=$A24)*(YEAR('M&A'!$D$2:$D$1000)=D$16)*('M&A'!$H$2:$H$1000<>""),'M&A'!$H$2:$H$1000),IF((Raises!$A$2:$A$1000=$A24)*(YEAR(Raises!$C$2:$C$1000)=D$16)*(Raises!$H$2:$H$1000<>""),Raises!$H$2:$H$1000)),"")
A26: SPREAD = public forward median (top grid) − private median (bottom), for comparable periods.
